rubim/__init__.py
rubim/client.py
rubim/config.py
rubim/cryption.py
rubim/rubino.py
rubim/tools.py
rubim-1.0.9.dist-info/LICENCE
rubim-1.0.9.dist-info/METADATA
rubim-1.0.9.dist-info/WHEEL
rubim-1.0.9.dist-info/top_level.txt
rubim-1.0.9.dist-info/RECORD
