Metadata-Version: 2.1
Name: rubim
Version: 1.0.9
Summary: Rubino API
Home-page: https://rubika.ir/rubim_py
Author: MMDreza
Author-email: vedaetext@gmail.com
License: MIT
Keywords: Rubim_library,Rubim,Rubika,Rubino,rubim,RUBIM,rubika,rubino
Classifier: Programming Language :: Python :: 3.6
Classifier: Programming Language :: Python :: 3.7
Classifier: Programming Language :: Python :: 3.8
Classifier: Programming Language :: Python :: 3.9
Classifier: Programming Language :: Python :: 3.10
Classifier: Programming Language :: Python :: 3.11
Classifier: License :: OSI Approved :: MIT License
Requires-Python: ~=3.7
License-File: LICENCE
Requires-Dist: requests
Requires-Dist: filetype
